rf_azure_sync/__init__.py
rf_azure_sync/rf_azure_sync.py
rf_azure_sync/rf_azure_sync_get.py
rf_azure_sync/rf_azure_sync_patch.py
rf_azure_sync/sync_utils.py
rf_azure_sync-1.0.1.dist-info/LICENSE
rf_azure_sync-1.0.1.dist-info/METADATA
rf_azure_sync-1.0.1.dist-info/WHEEL
rf_azure_sync-1.0.1.dist-info/entry_points.txt
rf_azure_sync-1.0.1.dist-info/top_level.txt
rf_azure_sync-1.0.1.dist-info/RECORD
