Metadata-Version: 2.1
Name: rf-azure-sync
Version: 1.0.1
Summary: Synchronization functionalities for Azure-related tasks.
Author-email: Fábio Ribeiro dos Santos Quispe <fabiorisantos1981@gmail.com>
Keywords: Azure,synchronization,robotframework
Classifier: Development Status :: 5 - Production/Stable
Classifier: Intended Audience :: Developers
Classifier: License :: OSI Approved :: MIT License
Classifier: Programming Language :: Python :: 3
Classifier: Programming Language :: Python :: 3.6
Classifier: Programming Language :: Python :: 3.7
Classifier: Programming Language :: Python :: 3.8
License-File: LICENSE
Requires-Dist: requests
